sigexec/__init__.py
sigexec/blocks/__init__.py
sigexec/blocks/doppler_processor.py
sigexec/blocks/matched_filter.py
sigexec/blocks/normalize.py
sigexec/blocks/pulse_stacker.py
sigexec/blocks/radar_generator.py
sigexec/blocks/to_magnitude_db.py
sigexec/core/__init__.py
sigexec/core/data.py
sigexec/core/graph.py
sigexec/core/port_optimizer.py
sigexec/diagnostics/__init__.py
sigexec/diagnostics/visualization.py
sigexec-2026.51.dist-info/METADATA
sigexec-2026.51.dist-info/WHEEL
sigexec-2026.51.dist-info/top_level.txt
sigexec-2026.51.dist-info/RECORD
