Metadata-Version: 2.4
Name: sigexec
Version: 2026.51
Summary: Signal processing execution graph using DAG and data classes
Author: Signal Processing Team
Classifier: Development Status :: 3 - Alpha
Classifier: Intended Audience :: Science/Research
Classifier: Programming Language :: Python :: 3
Classifier: Programming Language :: Python :: 3.7
Classifier: Programming Language :: Python :: 3.8
Classifier: Programming Language :: Python :: 3.9
Classifier: Programming Language :: Python :: 3.10
Classifier: Programming Language :: Python :: 3.11
Requires-Python: >=3.7
Requires-Dist: numpy>=1.20.0
Requires-Dist: scipy>=1.7.0
Requires-Dist: matplotlib>=3.3.0
Requires-Dist: plotly>=5.0.0
Provides-Extra: visualization
Requires-Dist: staticdash>=2025.1; extra == "visualization"
Requires-Dist: kaleido>=0.2.0; extra == "visualization"
Provides-Extra: dev
Requires-Dist: pytest>=7.0.0; extra == "dev"
Requires-Dist: pytest-cov>=4.0.0; extra == "dev"
Requires-Dist: build>=0.10.0; extra == "dev"
Requires-Dist: twine>=4.0.0; extra == "dev"
